pathlib_extensions/__init__.py
pathlib_extensions/__init__.pyi
pathlib_extensions/pathlib_extensions.py
pathlib_extensions/pathlib_extensions.pyi
pathlib_extensions/py.typed
pathlib_extensions-0.2.1.dist-info/LICENSE
pathlib_extensions-0.2.1.dist-info/METADATA
pathlib_extensions-0.2.1.dist-info/WHEEL
pathlib_extensions-0.2.1.dist-info/top_level.txt
pathlib_extensions-0.2.1.dist-info/RECORD
