Metadata-Version: 2.1
Name: pathlib-extensions
Version: 0.2.1
Summary: Backported and Experimental Filesystem Path Features for Python 3.6+
Home-page: https://github.com/ThScheeve/pathlib_extensions
Author: Thom Scheeve
Author-email: thscheeve@outlook.com
License: MIT
Project-URL: Changelog, https://github.com/ThScheeve/pathlib_extensions/blob/master/CHANGELOG.md
Project-URL: Bug Tracker, https://github.com/ThScheeve/pathlib_extensions/issues
Project-URL: Source Code, https://github.com/ThScheeve/pathlib_extensions
Keywords: backport,pathlib,path,filesystem
Platform: UNKNOWN
Classifier: Development Status :: 4 - Beta
Classifier: Environment :: Console
Classifier: Intended Audience :: Developers
Classifier: License :: OSI Approved :: MIT License
Classifier: Operating System :: OS Independent
Classifier: Natural Language :: English
Classifier: Programming Language :: Python :: 3
Classifier: Programming Language :: Python :: 3 :: Only
Classifier: Programming Language :: Python :: 3.6
Classifier: Programming Language :: Python :: 3.7
Classifier: Programming Language :: Python :: 3.8
Classifier: Programming Language :: Python :: 3.9
Classifier: Topic :: Software Development :: Libraries :: Python Modules
Classifier: Topic :: Utilities
Requires-Python: >=3.6
License-File: LICENSE
Requires-Dist: mimetypes-extensions
